pytest_aioboto3/__init__.py
pytest_aioboto3/aioboto3_fixtures.py
pytest_aioboto3/moto_fixtures.py
pytest_aioboto3-0.6.0.dist-info/LICENSE
pytest_aioboto3-0.6.0.dist-info/METADATA
pytest_aioboto3-0.6.0.dist-info/WHEEL
pytest_aioboto3-0.6.0.dist-info/entry_points.txt
pytest_aioboto3-0.6.0.dist-info/RECORD
