Metadata-Version: 2.3
Name: pytest-aioboto3
Version: 0.6.0
Summary: Aioboto3 Pytest with Moto
License: WTFPL
Keywords: pytest,aioboto3,moto
Author: Shipwell Engineering
Requires-Python: >=3.8,<4.0
Classifier: Framework :: Pytest
Classifier: License :: Other/Proprietary License
Classifier: License :: Public Domain
Classifier: Programming Language :: Python :: 3
Classifier: Programming Language :: Python :: 3.8
Classifier: Programming Language :: Python :: 3.9
Classifier: Programming Language :: Python :: 3.10
Classifier: Programming Language :: Python :: 3.11
Classifier: Programming Language :: Python :: 3.12
Classifier: Programming Language :: Python :: 3.13
Requires-Dist: aioboto3 (>=12.0.0)
Requires-Dist: moto[s3,server] (>=4.2.3)
Requires-Dist: requests (>=2.0)
Requires-Dist: types-aiobotocore[s3] (>=2.7.0)
Project-URL: Bug Tracker, https://github.com/phillipuniverse/pytest-aioboto3/issues
Project-URL: Homepage, https://github.com/phillipuniverse/pytest-aioboto3
Project-URL: Repository, https://github.com/phillipuniverse/pytest-aioboto3
